{
	"IC": {
		"name": "Canary Islands"
	},
	"BQ": {
		"name": "Caribbean Netherlands"
	},
	"EA": {
		"name": "Ceuta & Melilla"
	},
	"CG": {
		"name": "Congo - Brazzaville"
	},
	"CD": {
		"name": "Congo - Kinshasa"
	},
	"DG": {
		"name": "Diego Garcia"
	},
	"PS": {
		"name": "Palestinian Territories"
	},
	"KR": {
		"name": "South Korea"
	},
	"EH": {
		"name": "Western Sahara"
	},
	"AU": {
		"name": "Австралия"
	},
	"AT": {
		"name": "Австрия"
	},
	"AL": {
		"name": "Албания"
	},
	"DZ": {
		"name": "Алҷазоир"
	},
	"AE": {
		"name": "Аморатҳои Муттаҳидаи Араб"
	},
	"AI": {
		"name": "Ангилия"
	},
	"AO": {
		"name": "Ангола"
	},
	"AD": {
		"name": "Андорра"
	},
	"AQ": {
		"name": "Антарктида"
	},
	"AG": {
		"name": "Антигуа ва Барбуда"
	},
	"SA": {
		"name": "Арабистони Саудӣ"
	},
	"AR": {
		"name": "Аргентина"
	},
	"AM": {
		"name": "Арманистон"
	},
	"AW": {
		"name": "Аруба"
	},
	"AC": {
		"name": "Асунсон"
	},
	"AF": {
		"name": "Афғонистон"
	},
	"ZA": {
		"name": "Африкаи Ҷанубӣ"
	},
	"BS": {
		"name": "Багам"
	},
	"BD": {
		"name": "Бангладеш"
	},
	"BB": {
		"name": "Барбадос"
	},
	"BH": {
		"name": "Баҳрайн"
	},
	"BE": {
		"name": "Белгия"
	},
	"BZ": {
		"name": "Белиз"
	},
	"BY": {
		"name": "Белорус"
	},
	"BJ": {
		"name": "Бенин"
	},
	"BM": {
		"name": "Бермуда"
	},
	"BO": {
		"name": "Боливия"
	},
	"BA": {
		"name": "Босния ва Ҳерсеговина"
	},
	"BW": {
		"name": "Ботсвана"
	},
	"BR": {
		"name": "Бразилия"
	},
	"BN": {
		"name": "Бруней"
	},
	"BG": {
		"name": "Булғория"
	},
	"BF": {
		"name": "Буркина-Фасо"
	},
	"BI": {
		"name": "Бурунди"
	},
	"BT": {
		"name": "Бутон"
	},
	"VU": {
		"name": "Вануату"
	},
	"VE": {
		"name": "Венесуэла"
	},
	"VN": {
		"name": "Ветнам"
	},
	"GA": {
		"name": "Габон"
	},
	"HT": {
		"name": "Гаити"
	},
	"GY": {
		"name": "Гайана"
	},
	"GM": {
		"name": "Гамбия"
	},
	"GH": {
		"name": "Гана"
	},
	"GP": {
		"name": "Гваделупа"
	},
	"GT": {
		"name": "Гватемала"
	},
	"GF": {
		"name": "Гвианаи Фаронса"
	},
	"GN": {
		"name": "Гвинея"
	},
	"GW": {
		"name": "Гвинея-Бисау"
	},
	"GQ": {
		"name": "Гвинеяи Экваторӣ"
	},
	"DE": {
		"name": "Германия"
	},
	"GG": {
		"name": "Гернси"
	},
	"GI": {
		"name": "Гибралтар"
	},
	"HN": {
		"name": "Гондурас"
	},
	"GD": {
		"name": "Гренада"
	},
	"GL": {
		"name": "Гренландия"
	},
	"GU": {
		"name": "Гуам"
	},
	"GE": {
		"name": "Гурҷистон"
	},
	"DK": {
		"name": "Дания"
	},
	"DM": {
		"name": "Доминика"
	},
	"ZM": {
		"name": "Замбия"
	},
	"NZ": {
		"name": "Зеландияи Нав"
	},
	"ZW": {
		"name": "Зимбабве"
	},
	"US": {
		"name": "Иёлоти Муттаҳида"
	},
	"ID": {
		"name": "Индонезия"
	},
	"IE": {
		"name": "Ирландия"
	},
	"IQ": {
		"name": "Ироқ"
	},
	"IS": {
		"name": "Исландия"
	},
	"ES": {
		"name": "Испания"
	},
	"IL": {
		"name": "Исроил"
	},
	"IT": {
		"name": "Италия"
	},
	"CV": {
		"name": "Кабо-Верде"
	},
	"NC": {
		"name": "Каледонияи Нав"
	},
	"KH": {
		"name": "Камбоҷа"
	},
	"CM": {
		"name": "Камерун"
	},
	"CA": {
		"name": "Канада"
	},
	"KE": {
		"name": "Кения"
	},
	"CY": {
		"name": "Кипр"
	},
	"KI": {
		"name": "Кирибати"
	},
	"CO": {
		"name": "Колумбия"
	},
	"KM": {
		"name": "Комор"
	},
	"KP": {
		"name": "Кореяи Шимолӣ"
	},
	"XK": {
		"name": "Косово"
	},
	"CR": {
		"name": "Коста-Рика"
	},
	"CI": {
		"name": "Кот-д’Ивуар"
	},
	"CU": {
		"name": "Куба"
	},
	"CW": {
		"name": "Кюрасао"
	},
	"KZ": {
		"name": "Қазоқистон"
	},
	"IO": {
		"name": "Қаламрави Британия дар уқёнуси Ҳинд"
	},
	"QA": {
		"name": "Қатар"
	},
	"KG": {
		"name": "Қирғизистон"
	},
	"KW": {
		"name": "Қувайт"
	},
	"LA": {
		"name": "Лаос"
	},
	"LV": {
		"name": "Латвия"
	},
	"PL": {
		"name": "Лаҳистон"
	},
	"LS": {
		"name": "Лесото"
	},
	"LR": {
		"name": "Либерия"
	},
	"LY": {
		"name": "Либия"
	},
	"LT": {
		"name": "Литва"
	},
	"LI": {
		"name": "Лихтенштейн"
	},
	"LB": {
		"name": "Лубнон"
	},
	"LU": {
		"name": "Люксембург"
	},
	"MU": {
		"name": "Маврикий"
	},
	"MR": {
		"name": "Мавритания"
	},
	"MG": {
		"name": "Мадагаскар"
	},
	"YT": {
		"name": "Майотта"
	},
	"MO": {
		"name": "Макао (МММ)"
	},
	"MK": {
		"name": "Мақдун"
	},
	"MW": {
		"name": "Малави"
	},
	"MY": {
		"name": "Малайзия"
	},
	"MV": {
		"name": "Малдив"
	},
	"ML": {
		"name": "Мали"
	},
	"MT": {
		"name": "Малта"
	},
	"MA": {
		"name": "Марокаш"
	},
	"MQ": {
		"name": "Мартиника"
	},
	"HU": {
		"name": "Маҷористон"
	},
	"MX": {
		"name": "Мексика"
	},
	"TF": {
		"name": "Минтақаҳои Ҷанубии Фаронса"
	},
	"EG": {
		"name": "Миср"
	},
	"MZ": {
		"name": "Мозамбик"
	},
	"MD": {
		"name": "Молдова"
	},
	"MC": {
		"name": "Монако"
	},
	"MS": {
		"name": "Монтсеррат"
	},
	"MN": {
		"name": "Муғулистон"
	},
	"MM": {
		"name": "Мянма"
	},
	"NA": {
		"name": "Намибия"
	},
	"NR": {
		"name": "Науру"
	},
	"NP": {
		"name": "Непал"
	},
	"NE": {
		"name": "Нигер"
	},
	"NG": {
		"name": "Нигерия"
	},
	"NL": {
		"name": "Нидерландия"
	},
	"NI": {
		"name": "Никарагуа"
	},
	"NU": {
		"name": "Ниуэ"
	},
	"NO": {
		"name": "Норвегия"
	},
	"AZ": {
		"name": "Озарбойҷон"
	},
	"PW": {
		"name": "Палау"
	},
	"PA": {
		"name": "Панама"
	},
	"PG": {
		"name": "Папуа Гвинеяи Нав"
	},
	"PY": {
		"name": "Парагвай"
	},
	"PE": {
		"name": "Перу"
	},
	"PK": {
		"name": "Покистон"
	},
	"PF": {
		"name": "Полинезияи Фаронса"
	},
	"PT": {
		"name": "Португалия"
	},
	"PR": {
		"name": "Пуэрто-Рико"
	},
	"RE": {
		"name": "Реюнион"
	},
	"RW": {
		"name": "Руанда"
	},
	"RO": {
		"name": "Руминия"
	},
	"RU": {
		"name": "Русия"
	},
	"WS": {
		"name": "Самоа"
	},
	"AS": {
		"name": "Самоаи Америка"
	},
	"ST": {
		"name": "Сан Томе ва Принсипи"
	},
	"SM": {
		"name": "Сан-Марино"
	},
	"SZ": {
		"name": "Свазиленд"
	},
	"SC": {
		"name": "Сейшел"
	},
	"SN": {
		"name": "Сенегал"
	},
	"SH": {
		"name": "Сент Елена"
	},
	"BL": {
		"name": "Сент-Бартелми"
	},
	"VC": {
		"name": "Сент-Винсент ва Гренадина"
	},
	"KN": {
		"name": "Сент-Китс ва Невис"
	},
	"LC": {
		"name": "Сент-Люсия"
	},
	"PM": {
		"name": "Сент-Пер ва Микелон"
	},
	"RS": {
		"name": "Сербия"
	},
	"SL": {
		"name": "Сиерра-Леоне"
	},
	"SG": {
		"name": "Сингапур"
	},
	"SX": {
		"name": "Синт-Маартен"
	},
	"SK": {
		"name": "Словакия"
	},
	"SI": {
		"name": "Словения"
	},
	"SO": {
		"name": "Сомалӣ"
	},
	"SD": {
		"name": "Судон"
	},
	"SS": {
		"name": "Судони Ҷанубӣ"
	},
	"SR": {
		"name": "Суринам"
	},
	"SY": {
		"name": "Сурия"
	},
	"TH": {
		"name": "Таиланд"
	},
	"TW": {
		"name": "Тайван"
	},
	"TZ": {
		"name": "Танзания"
	},
	"TL": {
		"name": "Тимор-Лесте"
	},
	"TG": {
		"name": "Того"
	},
	"TK": {
		"name": "Токелау"
	},
	"TO": {
		"name": "Тонга"
	},
	"TJ": {
		"name": "Тоҷикистон"
	},
	"TT": {
		"name": "Тринидад ва Тобаго"
	},
	"TA": {
		"name": "Тристан-да-Куня"
	},
	"TV": {
		"name": "Тувалу"
	},
	"TN": {
		"name": "Тунис"
	},
	"TR": {
		"name": "Туркия"
	},
	"TM": {
		"name": "Туркманистон"
	},
	"UG": {
		"name": "Уганда"
	},
	"UZ": {
		"name": "Ӯзбекистон"
	},
	"UA": {
		"name": "Украина"
	},
	"OM": {
		"name": "Умон"
	},
	"WF": {
		"name": "Уоллис ва Футуна"
	},
	"JO": {
		"name": "Урдун"
	},
	"UY": {
		"name": "Уругвай"
	},
	"PH": {
		"name": "Филиппин"
	},
	"FI": {
		"name": "Финляндия"
	},
	"FJ": {
		"name": "Фиҷи"
	},
	"FR": {
		"name": "Франсия"
	},
	"CN": {
		"name": "Хитой"
	},
	"HR": {
		"name": "Хорватия"
	},
	"IN": {
		"name": "Ҳиндустон"
	},
	"HK": {
		"name": "Ҳонконг (МММ)"
	},
	"TD": {
		"name": "Чад"
	},
	"ME": {
		"name": "Черногория"
	},
	"CL": {
		"name": "Чили"
	},
	"CX": {
		"name": "Ҷазираи Крисмас"
	},
	"IM": {
		"name": "Ҷазираи Мэн"
	},
	"NF": {
		"name": "Ҷазираи Норфолк"
	},
	"MF": {
		"name": "Ҷазираи Сент-Мартин"
	},
	"AX": {
		"name": "Ҷазираҳои Аланд"
	},
	"VG": {
		"name": "Ҷазираҳои Виргини Британия"
	},
	"VI": {
		"name": "Ҷазираҳои Виргини ИМА"
	},
	"KY": {
		"name": "Ҷазираҳои Кайман"
	},
	"CC": {
		"name": "Ҷазираҳои Кокос (Килинг)"
	},
	"CK": {
		"name": "Ҷазираҳои Кук"
	},
	"MP": {
		"name": "Ҷазираҳои Марианаи Шимолӣ"
	},
	"MH": {
		"name": "Ҷазираҳои Маршалл"
	},
	"PN": {
		"name": "Ҷазираҳои Питкейрн"
	},
	"SB": {
		"name": "Ҷазираҳои Соломон"
	},
	"TC": {
		"name": "Ҷазираҳои Теркс ва Кайкос"
	},
	"FO": {
		"name": "Ҷазираҳои Фарер"
	},
	"FK": {
		"name": "Ҷазираҳои Фолкленд"
	},
	"UM": {
		"name": "Ҷазираҳои Хурди Дурдасти ИМА"
	},
	"JE": {
		"name": "Ҷерси"
	},
	"DJ": {
		"name": "Ҷибути"
	},
	"GS": {
		"name": "Ҷорҷияи Ҷанубӣ ва Ҷазираҳои Сандвич"
	},
	"CF": {
		"name": "Ҷумҳурии Африқои Марказӣ"
	},
	"DO": {
		"name": "Ҷумҳурии Доминикан"
	},
	"CZ": {
		"name": "Ҷумҳурии Чех"
	},
	"VA": {
		"name": "Шаҳри Вотикон"
	},
	"CH": {
		"name": "Швейтсария"
	},
	"SE": {
		"name": "Шветсия"
	},
	"GB": {
		"name": "Шоҳигарии Муттаҳида"
	},
	"SJ": {
		"name": "Шпитсберген ва Ян Майен"
	},
	"LK": {
		"name": "Шри-Ланка"
	},
	"FM": {
		"name": "Штатҳои Федеративии Микронезия"
	},
	"EC": {
		"name": "Эквадор"
	},
	"SV": {
		"name": "Эл-Салвадор"
	},
	"ER": {
		"name": "Эритрея"
	},
	"IR": {
		"name": "Эрон"
	},
	"EE": {
		"name": "Эстония"
	},
	"ET": {
		"name": "Эфиопия"
	},
	"GR": {
		"name": "Юнон"
	},
	"JM": {
		"name": "Ямайка"
	},
	"YE": {
		"name": "Яман"
	},
	"JP": {
		"name": "Япония"
	}
}