{
    "AC": {
        "name": "Ascension Island"
    },
    "AD": {
        "name": "Anḍurra"
    },
    "AE": {
        "name": "Imarat Tiεrabin Tidduklin"
    },
    "AF": {
        "name": "Afɣanistan"
    },
    "AG": {
        "name": "Antigwa d Barbuda"
    },
    "AI": {
        "name": "Angwilla"
    },
    "AL": {
        "name": "Albanya"
    },
    "AM": {
        "name": "Arminya"
    },
    "AO": {
        "name": "Angula"
    },
    "AQ": {
        "name": "Antarctica"
    },
    "AR": {
        "name": "Arjuntin"
    },
    "AS": {
        "name": "Samwa Imirikaniyyin"
    },
    "AT": {
        "name": "Ustriyya"
    },
    "AU": {
        "name": "Usṭralya"
    },
    "AW": {
        "name": "Aruba"
    },
    "AX": {
        "name": "Åland Islands"
    },
    "AZ": {
        "name": "Azerbiǧan"
    },
    "BA": {
        "name": "Busna-d-Hirsik"
    },
    "BB": {
        "name": "Barbadus"
    },
    "BD": {
        "name": "Bangladic"
    },
    "BE": {
        "name": "Beljika"
    },
    "BF": {
        "name": "Burkina Fasu"
    },
    "BG": {
        "name": "Belɣarya"
    },
    "BH": {
        "name": "Baḥrayn"
    },
    "BI": {
        "name": "Burundi"
    },
    "BJ": {
        "name": "Binin"
    },
    "BL": {
        "name": "St. Barthélemy"
    },
    "BM": {
        "name": "Birmuda"
    },
    "BN": {
        "name": "Brunay"
    },
    "BO": {
        "name": "Bulivya"
    },
    "BQ": {
        "name": "Caribbean Netherlands"
    },
    "BR": {
        "name": "Bṛazil"
    },
    "BS": {
        "name": "Bahamas"
    },
    "BT": {
        "name": "Buṭan"
    },
    "BW": {
        "name": "Butswana"
    },
    "BY": {
        "name": "Bilarusya"
    },
    "BZ": {
        "name": "Biliz"
    },
    "CA": {
        "name": "Kanada"
    },
    "CC": {
        "name": "Cocos (Keeling) Islands"
    },
    "CD": {
        "name": "Tagduda Tadimuqraṭit n Kungu"
    },
    "CF": {
        "name": "Tagduda n Afrika Wammas"
    },
    "CG": {
        "name": "Kungu"
    },
    "CH": {
        "name": "Swisra"
    },
    "CI": {
        "name": "Taɣazut n Uszer"
    },
    "CK": {
        "name": "Tigzirin n Kuk"
    },
    "CL": {
        "name": "Ccili"
    },
    "CM": {
        "name": "Kamerun"
    },
    "CN": {
        "name": "Ṣṣin"
    },
    "CO": {
        "name": "Kulumbya"
    },
    "CR": {
        "name": "Kusṭa Rika"
    },
    "CU": {
        "name": "kuba"
    },
    "CV": {
        "name": "Tigzirin n Iɣf Uzegzaw"
    },
    "CW": {
        "name": "Curaçao"
    },
    "CX": {
        "name": "Christmas Island"
    },
    "CY": {
        "name": "Qubrus"
    },
    "CZ": {
        "name": "Tagduda n Čik"
    },
    "DE": {
        "name": "Almanya"
    },
    "DG": {
        "name": "Diego Garcia"
    },
    "DJ": {
        "name": "Ǧibuti"
    },
    "DK": {
        "name": "Danmark"
    },
    "DM": {
        "name": "Ḍuminika"
    },
    "DO": {
        "name": "Tagduda n Ḍuminikan"
    },
    "DZ": {
        "name": "Dzayer"
    },
    "EA": {
        "name": "Ceuta & Melilla"
    },
    "EC": {
        "name": "Ikwaḍur"
    },
    "EE": {
        "name": "Isṭunya"
    },
    "EG": {
        "name": "Miṣr"
    },
    "EH": {
        "name": "Western Sahara"
    },
    "ER": {
        "name": "Iritrya"
    },
    "ES": {
        "name": "Sbanya"
    },
    "ET": {
        "name": "Ityupya"
    },
    "FI": {
        "name": "Finlanḍa"
    },
    "FJ": {
        "name": "Fiji"
    },
    "FK": {
        "name": "Tigzirin n Falkland"
    },
    "FM": {
        "name": "Mikrunizya"
    },
    "FO": {
        "name": "Faroe Islands"
    },
    "FR": {
        "name": "Fṛansa"
    },
    "GA": {
        "name": "Gabun"
    },
    "GB": {
        "name": "Tagelda Taddukelt"
    },
    "GD": {
        "name": "Grinada"
    },
    "GE": {
        "name": "Jyurjya"
    },
    "GF": {
        "name": "Guyana Tafransist"
    },
    "GG": {
        "name": "Guernsey"
    },
    "GH": {
        "name": "Ɣana"
    },
    "GI": {
        "name": "Jibralṭar"
    },
    "GL": {
        "name": "Grinlanḍa"
    },
    "GM": {
        "name": "Gambya"
    },
    "GN": {
        "name": "Ɣinya"
    },
    "GP": {
        "name": "Gwadalup"
    },
    "GQ": {
        "name": "Ɣinya Tikwaṭur it"
    },
    "GR": {
        "name": "Yunan"
    },
    "GS": {
        "name": "South Georgia & South Sandwich Islands"
    },
    "GT": {
        "name": "Gwatimala"
    },
    "GU": {
        "name": "Gwam"
    },
    "GW": {
        "name": "Ɣinya-Bissaw"
    },
    "GY": {
        "name": "Guyana"
    },
    "HK": {
        "name": "Hong Kong SAR China"
    },
    "HN": {
        "name": "Hinduras"
    },
    "HR": {
        "name": "Krwatya"
    },
    "HT": {
        "name": "Hayti"
    },
    "HU": {
        "name": "Henɣarya"
    },
    "IC": {
        "name": "Canary Islands"
    },
    "ID": {
        "name": "Indunizya"
    },
    "IE": {
        "name": "Irlanḍa"
    },
    "IL": {
        "name": "Israeil"
    },
    "IM": {
        "name": "Isle of Man"
    },
    "IN": {
        "name": "Hind"
    },
    "IO": {
        "name": "Amur n Agaraw Uhindi Ubṛiṭani"
    },
    "IQ": {
        "name": "Ɛiraq"
    },
    "IR": {
        "name": "Iran"
    },
    "IS": {
        "name": "Islanḍa"
    },
    "IT": {
        "name": "Iṭalya"
    },
    "JE": {
        "name": "Jersey"
    },
    "JM": {
        "name": "Jamayka"
    },
    "JO": {
        "name": "Urḍun"
    },
    "JP": {
        "name": "Jjappun"
    },
    "KE": {
        "name": "Kinya"
    },
    "KG": {
        "name": "Kirɣistan"
    },
    "KH": {
        "name": "Kambudj"
    },
    "KI": {
        "name": "Kiribati"
    },
    "KM": {
        "name": "Qumur"
    },
    "KN": {
        "name": "Santekits d Nivis"
    },
    "KP": {
        "name": "Kurya Tugafat"
    },
    "KR": {
        "name": "Kurya Tunẓult"
    },
    "KW": {
        "name": "Kuwwayt"
    },
    "KY": {
        "name": "Tigzirin n Kayman"
    },
    "KZ": {
        "name": "Kazaxistan"
    },
    "LA": {
        "name": "Laws"
    },
    "LB": {
        "name": "Lubnan"
    },
    "LC": {
        "name": "Santelusya"
    },
    "LI": {
        "name": "Lictencṭayn"
    },
    "LK": {
        "name": "Srilanka"
    },
    "LR": {
        "name": "Libirya"
    },
    "LS": {
        "name": "Lisuṭu"
    },
    "LT": {
        "name": "Litwanya"
    },
    "LU": {
        "name": "Liksumburg"
    },
    "LV": {
        "name": "Liṭṭunya"
    },
    "LY": {
        "name": "Libya"
    },
    "MA": {
        "name": "Meṛṛuk"
    },
    "MC": {
        "name": "Munaku"
    },
    "MD": {
        "name": "Mulḍavya"
    },
    "ME": {
        "name": "Montenegro"
    },
    "MF": {
        "name": "St. Martin"
    },
    "MG": {
        "name": "Madaɣacqar"
    },
    "MH": {
        "name": "Tigzirin n Marcal"
    },
    "MK": {
        "name": "Maqdunya"
    },
    "ML": {
        "name": "Mali"
    },
    "MM": {
        "name": "Myanmar"
    },
    "MN": {
        "name": "Manɣulya"
    },
    "MO": {
        "name": "Macau SAR China"
    },
    "MP": {
        "name": "Tigzirin n Maryana Tugafat"
    },
    "MQ": {
        "name": "Martinik"
    },
    "MR": {
        "name": "Muritanya"
    },
    "MS": {
        "name": "Muntsirra"
    },
    "MT": {
        "name": "Malṭa"
    },
    "MU": {
        "name": "Muris"
    },
    "MV": {
        "name": "Maldiv"
    },
    "MW": {
        "name": "Malawi"
    },
    "MX": {
        "name": "Miksik"
    },
    "MY": {
        "name": "Malizya"
    },
    "MZ": {
        "name": "Muzambiq"
    },
    "NA": {
        "name": "Namibya"
    },
    "NC": {
        "name": "kalidunya Tamaynut"
    },
    "NE": {
        "name": "Nnijer"
    },
    "NF": {
        "name": "Tigzirt Nurfulk"
    },
    "NG": {
        "name": "Nijiria"
    },
    "NI": {
        "name": "Nikaragwa"
    },
    "NL": {
        "name": "Hulanḍa"
    },
    "NO": {
        "name": "Nnurwij"
    },
    "NP": {
        "name": "Nippal"
    },
    "NR": {
        "name": "Nawru"
    },
    "NU": {
        "name": "Niwi"
    },
    "NZ": {
        "name": "Zilanḍa Tamaynut"
    },
    "OM": {
        "name": "Ɛumman"
    },
    "PA": {
        "name": "Panama"
    },
    "PE": {
        "name": "Piru"
    },
    "PF": {
        "name": "Pulinizya Tafransist"
    },
    "PG": {
        "name": "Papwa Ɣinya Tamaynut"
    },
    "PH": {
        "name": "Filippin"
    },
    "PK": {
        "name": "Pakistan"
    },
    "PL": {
        "name": "Pulunya"
    },
    "PM": {
        "name": "Santepyir d Mikelun"
    },
    "PN": {
        "name": "Pitkirn"
    },
    "PR": {
        "name": "Purturiku"
    },
    "PS": {
        "name": "Agemmaḍ Ugut d Ɣazza Ifilisṭiniyen"
    },
    "PT": {
        "name": "Purtuɣal"
    },
    "PW": {
        "name": "Palu"
    },
    "PY": {
        "name": "Paragway"
    },
    "QA": {
        "name": "Qaṭar"
    },
    "RE": {
        "name": "Riyyunyun"
    },
    "RO": {
        "name": "Ṛumanya"
    },
    "RS": {
        "name": "Serbia"
    },
    "RU": {
        "name": "Rusya"
    },
    "RW": {
        "name": "Ruwwanḍa"
    },
    "SA": {
        "name": "Ssaεudiyya Taεrabt"
    },
    "SB": {
        "name": "Tigzirin n Salumun"
    },
    "SC": {
        "name": "Ssicil"
    },
    "SD": {
        "name": "Ssudan"
    },
    "SE": {
        "name": "Ssewwid"
    },
    "SG": {
        "name": "Sanɣafura"
    },
    "SH": {
        "name": "Santehilin"
    },
    "SI": {
        "name": "Sluvinya"
    },
    "SJ": {
        "name": "Svalbard & Jan Mayen"
    },
    "SK": {
        "name": "Sluvakya"
    },
    "SL": {
        "name": "Siralyun"
    },
    "SM": {
        "name": "Sanmarinu"
    },
    "SN": {
        "name": "Ssiniɣal"
    },
    "SO": {
        "name": "Ṣṣumal"
    },
    "SR": {
        "name": "Surinam"
    },
    "SS": {
        "name": "South Sudan"
    },
    "ST": {
        "name": "Sawṭumi d Prinsip"
    },
    "SV": {
        "name": "Salvaḍur"
    },
    "SX": {
        "name": "Sint Maarten"
    },
    "SY": {
        "name": "Surya"
    },
    "SZ": {
        "name": "Swazilanḍa"
    },
    "TA": {
        "name": "Tristan da Cunha"
    },
    "TC": {
        "name": "Tigzirin Turkiyyin d Tikaykusin"
    },
    "TD": {
        "name": "Tcad"
    },
    "TF": {
        "name": "French Southern Territories"
    },
    "TG": {
        "name": "Ṭṭugu"
    },
    "TH": {
        "name": "Ṭaylanḍa"
    },
    "TJ": {
        "name": "Ṭaǧikistan"
    },
    "TK": {
        "name": "Tuklu"
    },
    "TL": {
        "name": "Timur Tagmuṭ"
    },
    "TM": {
        "name": "Turkmanistan"
    },
    "TN": {
        "name": "Tunes"
    },
    "TO": {
        "name": "Ṭunga"
    },
    "TR": {
        "name": "Turkya"
    },
    "TT": {
        "name": "Trinidad d Ṭubagu"
    },
    "TV": {
        "name": "Ṭuvalu"
    },
    "TW": {
        "name": "Ṭaywan"
    },
    "TZ": {
        "name": "Ṭanzanya"
    },
    "UA": {
        "name": "Ukranya"
    },
    "UG": {
        "name": "Uɣanda"
    },
    "UM": {
        "name": "U.S. Outlying Islands"
    },
    "US": {
        "name": "Iwunak Idduklen n Amirika"
    },
    "UY": {
        "name": "Urugway"
    },
    "UZ": {
        "name": "Uzbakistan"
    },
    "VA": {
        "name": "Awank iɣrem n Vatikan"
    },
    "VC": {
        "name": "Santevinsent d Grinadin"
    },
    "VE": {
        "name": "Vinzwilla"
    },
    "VG": {
        "name": "Tigzirin (Virgin) Tibṛiṭaniyin"
    },
    "VI": {
        "name": "Tigzirin n Virjin n Iwunak Yedduklen"
    },
    "VN": {
        "name": "Viṭnam"
    },
    "VU": {
        "name": "Vanwatu"
    },
    "WF": {
        "name": "Walis d Futuna"
    },
    "WS": {
        "name": "Samwa"
    },
    "XK": {
        "name": "Kosovo"
    },
    "YE": {
        "name": "Yaman"
    },
    "YT": {
        "name": "Mayuṭ"
    },
    "ZA": {
        "name": "Tafrikt Tunẓul"
    },
    "ZM": {
        "name": "Zambya"
    },
    "ZW": {
        "name": "Zimbabwi"
    }
}